laravel_queue/__about__.py
laravel_queue/__init__.py
laravel_queue-0.0.16.dist-info/METADATA
laravel_queue-0.0.16.dist-info/WHEEL
laravel_queue-0.0.16.dist-info/licenses/LICENSE
laravel_queue-0.0.16.dist-info/RECORD
