Metadata-Version: 2.3
Name: laravel_queue
Version: 0.0.16
Summary: Reads from a Laravel queue
Project-URL: Repository, https://github.com/2ndnaturewater/python-laravel-queue
Project-URL: Issues, https://github.com/2ndnaturewater/python-laravel-queue/issues
Author-email: 2NDNATURE <info@2ndnaturewater.com>
License-File: LICENSE
Classifier: License :: OSI Approved :: MIT License
Classifier: Operating System :: OS Independent
Classifier: Programming Language :: Python :: 3
Requires-Python: >=3.8
Requires-Dist: phpserialize
Requires-Dist: psycopg2
